arvestust/__init__.py
arvestust/api.py
arvestust/apps.py
arvestust/requires.py
arvestust/urls.py
arvestust/admin/__init__.py
arvestust/admin/comment.py
arvestust/admin/file.py
arvestust/admin/image.py
arvestust/admin/tag.py
arvestust/admin/actions/__init__.py
arvestust/admin/helpers/__init__.py
arvestust/admin/inlines/__init__.py
arvestust/admin/inlines/comment.py
arvestust/admin/inlines/file.py
arvestust/admin/inlines/image.py
arvestust/admin/inlines/tag.py
arvestust/admin/permissions/__init__.py
arvestust/audit/__init__.py
arvestust/fixtures/__init__.py
arvestust/fixtures/helpers/__init__.py
arvestust/forms/__init__.py
arvestust/forms/arvestust_record.py
arvestust/forms/comment.py
arvestust/forms/file.py
arvestust/forms/image.py
arvestust/forms/tag.py
arvestust/forms/helpers/__init__.py
arvestust/middleware/__init__.py
arvestust/middleware/helpers/__init__.py
arvestust/migrations/0001_initial.py
arvestust/migrations/0002_auto_20200729_1639.py
arvestust/migrations/0003_auto_20200729_1653.py
arvestust/migrations/0004_auto_20200729_1701.py
arvestust/migrations/0005_auto_20200729_1925.py
arvestust/migrations/0006_auto_20200730_1513.py
arvestust/migrations/0007_auto_20200730_1513.py
arvestust/migrations/0008_auto_20200730_1516.py
arvestust/migrations/0009_auto_20200730_1900.py
arvestust/migrations/0010_auto_20200803_0050.py
arvestust/migrations/0011_auto_20200803_2019.py
arvestust/migrations/0012_auto_20200812_2121.py
arvestust/migrations/__init__.py
arvestust/models/__init__.py
arvestust/models/activity.py
arvestust/models/comment.py
arvestust/models/file.py
arvestust/models/image.py
arvestust/models/tag.py
arvestust/models/abstracts/__init__.py
arvestust/models/abstracts/file.py
arvestust/models/abstracts/record.py
arvestust/models/abstracts/user_record.py
arvestust/models/helpers/__init__.py
arvestust/models/managers/__init__.py
arvestust/models/managers/activity.py
arvestust/models/managers/arvestust_file.py
arvestust/models/managers/comment.py
django_arvestust-0.7.1.dist-info/LICENSE.md
django_arvestust-0.7.1.dist-info/METADATA
django_arvestust-0.7.1.dist-info/WHEEL
django_arvestust-0.7.1.dist-info/top_level.txt
django_arvestust-0.7.1.dist-info/RECORD
