Metadata-Version: 2.1
Name: django-arvestust
Version: 0.7.1
Summary: A Django app for file management and record-keeping
Home-page: https://www.github.com/lehvitus/arvestust
Author: Leo Neto
Author-email: projects@lehvitus.com
License: BSD-3-Clause
Keywords: django files
Platform: UNKNOWN
Classifier: Environment :: Web Environment
Classifier: Framework :: Django
Classifier: Framework :: Django :: 2.2
Classifier: Framework :: Django :: 3.0
Classifier: Intended Audience :: Developers
Classifier: License :: OSI Approved :: BSD License
Classifier: Operating System :: OS Independent
Classifier: Programming Language :: Python
Classifier: Programming Language :: Python :: 3 :: Only
Classifier: Programming Language :: Python :: 3.4
Classifier: Programming Language :: Python :: 3.5
Classifier: Programming Language :: Python :: 3.6
Classifier: Programming Language :: Python :: 3.7
Classifier: Programming Language :: Python :: 3.8
Classifier: Topic :: Internet :: WWW/HTTP
Classifier: Topic :: Internet :: WWW/HTTP :: Dynamic Content
Requires-Python: >=3.4
Requires-Dist: django (>=2.2)
Requires-Dist: django-crispy-forms (>=1.9.1)
Requires-Dist: inflection (==0.5.0)
Requires-Dist: python-magic (>=0.4.18)
